README
README.md
setup.cfg
setup.py
rayter/__init__.py
rayter/game_parser.py
rayter/main.py
rayter/player.py
rayter/rater.py
rayter.egg-info/PKG-INFO
rayter.egg-info/SOURCES.txt
rayter.egg-info/dependency_links.txt
rayter.egg-info/entry_points.txt
rayter.egg-info/not-zip-safe
rayter.egg-info/top_level.txt