Metadata-Version: 2.1
Name: rayter
Version: 2.1.0
Summary: Game rating command line tool and python library
Home-page: https://github.com/peterjaric/rayter
License: MIT
Project-URL: Documentation, https://github.com/peterjaric/rayter
Project-URL: Code, https://github.com/peterjaric/rayter
Project-URL: Issue tracker, https://github.com/peterjaric/rayter/issues
Keywords: game,rating,elo,python
Classifier: Development Status :: 5 - Production/Stable
Classifier: Operating System :: OS Independent
Classifier: Programming Language :: Python
Classifier: Programming Language :: Python :: 3
Classifier: Programming Language :: Python :: 3 :: Only
Classifier: Topic :: Games/Entertainment
Requires-Python: >=3.6
